jira_lazy/__init__.py
jira_lazy/collection_endpoint.py
jira_lazy/session.py
jira_lazy-0.0.1.dist-info/METADATA
jira_lazy-0.0.1.dist-info/WHEEL
jira_lazy-0.0.1.dist-info/licenses/LICENSE
jira_lazy-0.0.1.dist-info/RECORD
