Metadata-Version: 2.1
Name: jira_lazy
Version: 0.0.1
Summary: A lazy Jira library for lazy developers
Author-email: Marcus Harrison <marcus@harrisonland.co.uk>
License-File: LICENSE
Classifier: License :: OSI Approved :: GNU General Public License v3 or later (GPLv3+)
Classifier: Operating System :: OS Independent
Classifier: Programming Language :: Python :: 3
Requires-Python: >=3.10.12
Requires-Dist: requests>=2.31.0
